dictnodefinder/__init__.py
dictnodefinder/_compat.py
dictnodefinder/version.py
dictnodefinder-1.0.1.dev1.dist-info/AUTHORS
dictnodefinder-1.0.1.dev1.dist-info/LICENSE
dictnodefinder-1.0.1.dev1.dist-info/METADATA
dictnodefinder-1.0.1.dev1.dist-info/WHEEL
dictnodefinder-1.0.1.dev1.dist-info/top_level.txt
dictnodefinder-1.0.1.dev1.dist-info/RECORD
